main.py
dvoa_cli-1.0.dist-info/METADATA
dvoa_cli-1.0.dist-info/WHEEL
dvoa_cli-1.0.dist-info/entry_points.txt
dvoa_cli-1.0.dist-info/top_level.txt
dvoa_cli-1.0.dist-info/RECORD
