Metadata-Version: 2.4
Name: dvoa-cli
Version: 1.0
Summary: VOA CLI Tool : Just a frontend of VOA API https://gthub.com/senani-derradji/VOA
Author: Derradji Senani
Requires-Python: >=3.9
Requires-Dist: click>=8.0
Requires-Dist: python-dotenv
Requires-Dist: redis
